LICENSE
README.md
setup.py
streamlit_book/__init__.py
streamlit_book/admin.py
streamlit_book/answers.py
streamlit_book/book_config.py
streamlit_book/chapter_config.py
streamlit_book/colored_expanders.py
streamlit_book/echo.py
streamlit_book/file_reader.py
streamlit_book/floating_button.py
streamlit_book/helpers.py
streamlit_book/keywords.py
streamlit_book/login.py
streamlit_book/render.py
streamlit_book/render_code_input.py
streamlit_book/render_multiple_choice.py
streamlit_book/render_single_choice.py
streamlit_book/render_text_input.py
streamlit_book/render_to_do_list.py
streamlit_book/render_true_or_false.py
streamlit_book/social_media.py
streamlit_slides.egg-info/PKG-INFO
streamlit_slides.egg-info/SOURCES.txt
streamlit_slides.egg-info/dependency_links.txt
streamlit_slides.egg-info/requires.txt
streamlit_slides.egg-info/top_level.txt