Metadata-Version: 2.1
Name: streamlit-slides
Version: 0.7.8
Summary: A streamlit companion library to create a interactive reader for the content on a given folder
Home-page: https://github.com/sebastiandres/streamlit_book
Author: Sebastián Flores Benner
Author-email: sebastiandres@gmail.com
Requires-Python: >=3.7
License-File: LICENSE
Requires-Dist: streamlit>=0.63
Requires-Dist: streamlit-option-menu
Provides-Extra: devel
Requires-Dist: wheel; extra == "devel"
Requires-Dist: pytest==7.4.0; extra == "devel"
Requires-Dist: playwright==1.36.0; extra == "devel"
Requires-Dist: requests==2.31.0; extra == "devel"
Requires-Dist: pytest-playwright-snapshot==1.0; extra == "devel"
Requires-Dist: pytest-rerunfailures==12.0; extra == "devel"
